<?xml version="1.0" encoding="utf-8" ?>
<dwsync>
<file name="album.html" server="C:/xampp/htdocs/Gustavo_FazFesta_teste/" local="131606673680000000" remote="131606673680000000" Dst="2" />
<file name="cadastrocliente.html" server="C:/xampp/htdocs/Gustavo_FazFesta_teste/" local="131606673680000000" remote="131606673680000000" Dst="2" />
<file name="contato.html" server="C:/xampp/htdocs/Gustavo_FazFesta_teste/" local="131606673680000000" remote="131606673680000000" Dst="2" />
<file name="controleusuarios.html" server="C:/xampp/htdocs/Gustavo_FazFesta_teste/" local="131606673680000000" remote="131606673680000000" Dst="2" />
<file name="dadosconta.html" server="C:/xampp/htdocs/Gustavo_FazFesta_teste/" local="131606673680000000" remote="131606673680000000" Dst="2" />
<file name="eventos.html" server="C:/xampp/htdocs/Gustavo_FazFesta_teste/" local="131606673680000000" remote="131606673680000000" Dst="2" />
<file name="index.html" server="C:/xampp/htdocs/Gustavo_FazFesta_teste/" local="131606673700000000" remote="131606673700000000" Dst="2" />
<file name="loginecadastro.html" server="C:/xampp/htdocs/Gustavo_FazFesta_teste/" local="131606673700000000" remote="131606673700000000" Dst="2" />
<file name="menu.html" server="C:/xampp/htdocs/Gustavo_FazFesta_teste/" local="131606673720000000" remote="131606673720000000" Dst="2" />
<file name="produtos.html" server="C:/xampp/htdocs/Gustavo_FazFesta_teste/" local="131606673720000000" remote="131606673720000000" Dst="2" />
<file name="sobre.html" server="C:/xampp/htdocs/Gustavo_FazFesta_teste/" local="131606673720000000" remote="131606673720000000" Dst="2" />
</dwsync>